{"8itehqPb134Cjl3WnyDn9g==":"crates-stored-2000x1203.png","o0ni+VtEI9ONNMjnBCPqTA==":"communal%20table-480x480.jpg","JIOx5v0cBtEAgGR3mefdwA==":"ambassador-installations-logo-122x12.png","AEOaI/ct34RLX6Rjt28Kew==":"ambassador%20logo-421x66.png","A0KH2gR2ehEie8RkrHFKQg==":"installations-122x24.png","LlkdshUkVebFV9f08vwE9w==":"a%20logo-113x49.png","pa5Dkwo/T1qgW/t0h+fQvA==":"background5.jpg","0yKmaFtUGQE1UEx1aBlZRw==":"chamberofcommerce-650x413.png","y+/Af4QaKPpTgT0ieIDTaQ==":"mm-logo-38x12.png","1KHS4AGNCXvnVqWjXncjPw==":"mm-logo-1-38x12.png","la+99YcFVab2ff4J1ygOxA==":"mm-logo-60x20.png","W6SLb8dS9sTUA6z7draorg==":"stash-logo-200x38.png","DicNlnJ6xgGh69d7h1yIcg==":"stash-logo-1-200x38.png","sg5gEkEyC1Llf4zv5kQVmg==":"stash-logo-217x71.png","JZsM9SKl0m6WL4Px8ltYxg==":"mm-logo-200x65.png"}